verna/__init__.py
verna/names.py
verna/verna.py
verna-0.0.2.dist-info/LICENSE.md
verna-0.0.2.dist-info/METADATA
verna-0.0.2.dist-info/WHEEL
verna-0.0.2.dist-info/top_level.txt
verna-0.0.2.dist-info/RECORD
