Metadata-Version: 2.1
Name: verna
Version: 0.0.2
Summary: A simple module to handle colors
Home-page: https://github.com/ju-sh/verna
Author: Julin S
Author-email: 
License: UNKNOWN
Project-URL: Changelog, https://github.com/ju-sh/verna/CHANGELOG.md
Project-URL: Issue Tracker, https://github.com/ju-sh/verna/issues
Platform: UNKNOWN
Classifier: Programming Language :: Python :: 3
Classifier: Programming Language :: Python :: 3.6
Classifier: Programming Language :: Python :: 3.7
Classifier: Programming Language :: Python :: 3.8
Classifier: Programming Language :: Python :: 3.9
Classifier: Topic :: Software Development :: Libraries :: Python Modules
Classifier: Development Status :: 3 - Alpha
Classifier: Operating System :: OS Independent
Classifier: License :: OSI Approved :: MIT License
Requires-Python: >=3.6
